ollama2a/__init__.py
ollama2a/agent_executor.py
ollama2a/main.py
ollama2a/ollama_manager.py
ollama2a-1.0.0.dist-info/licenses/LICENSE
ollama2a-1.0.0.dist-info/METADATA
ollama2a-1.0.0.dist-info/WHEEL
ollama2a-1.0.0.dist-info/top_level.txt
ollama2a-1.0.0.dist-info/RECORD
