Metadata-Version: 2.4
Name: ollama2a
Version: 1.0.0
Summary: A Python library for running Ollama agents with automated server management
Home-page: https://github.com/thijshakkenbergecolab/ollama2a
Author: Thijs Hakkenberg
Author-email: Thijs Hakkenberg <thijs.hakkenberg@ecolab.com>
License: MIT
Project-URL: Homepage, https://github.com/thijshakkenbergecolab/ollama2a
Project-URL: Repository, https://github.com/thijshakkenbergecolab/ollama2a
Project-URL: Issues, https://github.com/thijshakkenbergecolab/ollama2aissues
Project-URL: Documentation, https://github.com/thijshakkenbergecolab/ollama2a#readme
Classifier: Development Status :: 3 - Alpha
Classifier: Intended Audience :: Developers
Classifier: Topic :: Software Development :: Libraries :: Python Modules
Classifier: Topic :: Scientific/Engineering :: Artificial Intelligence
Classifier: License :: OSI Approved :: MIT License
Classifier: Programming Language :: Python :: 3
Classifier: Programming Language :: Python :: 3.9
Classifier: Programming Language :: Python :: 3.10
Classifier: Programming Language :: Python :: 3.11
Classifier: Programming Language :: Python :: 3.12
Requires-Python: >=3.9
License-File: LICENSE
Requires-Dist: pydantic-ai>=0.0.14
Requires-Dist: ollama<1.0.0,>=0.5.1
Requires-Dist: fasta2a<1.0.0,>=0.3.5
Requires-Dist: psutil<8.0.0,>=5.8.0
Requires-Dist: a2a-sdk
Requires-Dist: openai<2.0.0,>=1.0.0
Requires-Dist: httpx<1.0.0,>=0.24.0
Provides-Extra: dev
Requires-Dist: pytest>=7.0.0; extra == "dev"
Requires-Dist: pytest-asyncio>=0.21.0; extra == "dev"
Requires-Dist: pytest-cov>=4.0.0; extra == "dev"
Requires-Dist: black>=22.0.0; extra == "dev"
Requires-Dist: isort>=5.10.0; extra == "dev"
Requires-Dist: flake8>=4.0.0; extra == "dev"
Requires-Dist: mypy>=1.0.0; extra == "dev"
Provides-Extra: test
Requires-Dist: pytest>=7.0.0; extra == "test"
Requires-Dist: pytest-asyncio>=0.21.0; extra == "test"
Requires-Dist: pytest-cov>=4.0.0; extra == "test"
Dynamic: author
Dynamic: home-page
Dynamic: license-file
Dynamic: requires-python
